dxf_viewer/__init__.py
dxf_viewer/core.py
dxf_viewer/static/Panel.js
dxf_viewer/static/Panel.js.map
dxf_viewer/static/.vite/manifest.json
inventree_dxf_viewer-0.1.0.dist-info/licenses/LICENSE
inventree_dxf_viewer-0.1.0.dist-info/METADATA
inventree_dxf_viewer-0.1.0.dist-info/WHEEL
inventree_dxf_viewer-0.1.0.dist-info/entry_points.txt
inventree_dxf_viewer-0.1.0.dist-info/top_level.txt
inventree_dxf_viewer-0.1.0.dist-info/RECORD
