Metadata-Version: 2.4
Name: inventree-dxf-viewer
Version: 0.1.0
Summary: View DXF files if provided as an attachment to a part
Author-email: Alec Delaney <tekktrik@tekktrik.dev>
License-Expression: MIT
Project-URL: Homepage, https://github.com/tekktrik/inventree-dxf-viewer-plugin
Keywords: inventree,plugin
Classifier: Programming Language :: Python :: 3
Classifier: Operating System :: OS Independent
Classifier: Framework :: InvenTree
Requires-Python: >=3.9
License-File: LICENSE
Dynamic: license-file
